pyxodr_omega_prime/__init__.py
pyxodr_omega_prime/geometries/__init__.py
pyxodr_omega_prime/geometries/_standard_spiral.py
pyxodr_omega_prime/geometries/arc.py
pyxodr_omega_prime/geometries/base.py
pyxodr_omega_prime/geometries/cubic_polynom.py
pyxodr_omega_prime/geometries/multi.py
pyxodr_omega_prime/geometries/spiral.py
pyxodr_omega_prime/road_objects/__init__.py
pyxodr_omega_prime/road_objects/junction.py
pyxodr_omega_prime/road_objects/lane.py
pyxodr_omega_prime/road_objects/lane_section.py
pyxodr_omega_prime/road_objects/network.py
pyxodr_omega_prime/road_objects/road.py
pyxodr_omega_prime/utils/__init__.py
pyxodr_omega_prime/utils/array.py
pyxodr_omega_prime/utils/cached_property.py
pyxodr_omega_prime/utils/curved_text.py
pyxodr_omega_prime-0.1.5.dist-info/licenses/LICENSE.md
pyxodr_omega_prime-0.1.5.dist-info/METADATA
pyxodr_omega_prime-0.1.5.dist-info/WHEEL
pyxodr_omega_prime-0.1.5.dist-info/top_level.txt
pyxodr_omega_prime-0.1.5.dist-info/RECORD
