Metadata-Version: 2.4
Name: pyxodr-omega-prime
Version: 0.1.5
Summary: Read OpenDRIVE files.
Author-email: Stamatis Chrysanthidis <stamchry@gmail.com>
Project-URL: Homepage, https://github.com/stamchry/pyxodr/tree/omega-prime
Classifier: Programming Language :: Python :: 3
Classifier: License :: OSI Approved :: MIT License
Classifier: Operating System :: OS Independent
Requires-Python: >=3.7
License-File: LICENSE.md
Requires-Dist: lxml>=4.9.1
Requires-Dist: matplotlib>=3.5.0
Requires-Dist: numpy>=1.21.0
Requires-Dist: rich>=12.6.0
Requires-Dist: scipy>=1.7.0
Requires-Dist: Shapely>=1.8.4
Provides-Extra: dev
Requires-Dist: pytest>=7.1.3; extra == "dev"
Dynamic: license-file
